HeyDB/__init__.py
HeyDB-1.0.0.dist-info/LICENSE
HeyDB-1.0.0.dist-info/METADATA
HeyDB-1.0.0.dist-info/WHEEL
HeyDB-1.0.0.dist-info/top_level.txt
HeyDB-1.0.0.dist-info/RECORD
