Metadata-Version: 2.1
Name: HeyDB
Version: 1.0.0
Summary: NoSQL内嵌数据库
Home-page: https://github.com/CNlongY-Py/HeyDB
Author: CNlongY
Author-email: T3464356490@outlook.com
Classifier: Programming Language :: Python :: 3
Classifier: License :: OSI Approved :: MIT License
Classifier: Operating System :: OS Independent
License-File: LICENSE
